dyPi/__init__.py
dypi-0.0.1b1.dist-info/METADATA
dypi-0.0.1b1.dist-info/WHEEL
dypi-0.0.1b1.dist-info/top_level.txt
dypi-0.0.1b1.dist-info/RECORD
