Metadata-Version: 2.1
Name: dypi
Version: 0.0.1b1
Summary: A simple package for calculating factorial and Fibonacci sequences.
Home-page: https://github.com/imooger/DyPi
Author: Marek Jindrich
Author-email: imooger@gmail.com
Classifier: Programming Language :: Python :: 3
Classifier: License :: OSI Approved :: MIT License
Classifier: Operating System :: OS Independent
Classifier: Development Status :: 4 - Beta
Classifier: Intended Audience :: Developers
Classifier: Topic :: Software Development :: Libraries
Requires-Python: >=3.6
